odoo/addons/crm_sale_secondary_salesperson/README.rst
odoo/addons/crm_sale_secondary_salesperson/__init__.py
odoo/addons/crm_sale_secondary_salesperson/__manifest__.py
odoo/addons/crm_sale_secondary_salesperson/i18n/crm_sale_secondary_salesperson.pot
odoo/addons/crm_sale_secondary_salesperson/i18n/es.po
odoo/addons/crm_sale_secondary_salesperson/i18n/it.po
odoo/addons/crm_sale_secondary_salesperson/models/__init__.py
odoo/addons/crm_sale_secondary_salesperson/models/sale_order.py
odoo/addons/crm_sale_secondary_salesperson/readme/CONTRIBUTORS.rst
odoo/addons/crm_sale_secondary_salesperson/readme/DESCRIPTION.rst
odoo/addons/crm_sale_secondary_salesperson/static/description/icon.png
odoo/addons/crm_sale_secondary_salesperson/static/description/index.html
odoo/addons/crm_sale_secondary_salesperson/tests/__init__.py
odoo/addons/crm_sale_secondary_salesperson/tests/test_sale_order.py
odoo13_addon_crm_sale_secondary_salesperson-13.0.1.0.1.dev6.dist-info/METADATA
odoo13_addon_crm_sale_secondary_salesperson-13.0.1.0.1.dev6.dist-info/WHEEL
odoo13_addon_crm_sale_secondary_salesperson-13.0.1.0.1.dev6.dist-info/top_level.txt
odoo13_addon_crm_sale_secondary_salesperson-13.0.1.0.1.dev6.dist-info/RECORD
